app.py
python_sbx-2.0.0.dist-info/licenses/LICENSE
python_sbx-2.0.0.dist-info/METADATA
python_sbx-2.0.0.dist-info/WHEEL
python_sbx-2.0.0.dist-info/entry_points.txt
python_sbx-2.0.0.dist-info/top_level.txt
python_sbx-2.0.0.dist-info/RECORD
